{
	"success": 1,
	"code": "OK",
	"msg": "OK",
	"data": {
		"rowcount": 1,
		"totalrows": 1,
		"estimatedrows": false,
		"pagesize": 0,
		"pagecount": null,
		"page": 1,
		"offset": 0,
		"startrow": 0,
		"resultset": [
			{
				"id": "363",
				"code": "ELYSIUM",
				"description": "The ancestral home of the Tevarin species, Elysium was incorporated into the UPE at the end of the First Tevarin War (2542-2546) and cleared for Human habitation. The system became the focal point of the Second Tevarin War (2603-2610) when the shattered remnants of Warlord Corath\u2019Thal\u2019s fleet crashed into their former homeworld to end the conflict. \n",
				"frost_line": "8.44000000",
				"habitable_zone_inner": "1.59000000",
				"habitable_zone_outer": "2.61000000",
				"info_url": null,
				"name": "Elysium",
				"position_x": "-32.41680100",
				"position_y": "-40.17849300",
				"position_z": "-20.80187600",
				"shader_data": {
					"lightColor": "#ffffff",
					"starfield": {
						"radius": 3,
						"count": 200,
						"sizeMin": 1,
						"sizeMax": 1,
						"color1": "rgb(128,128,128)",
						"color2": "rgb(100,100,100)"
					},
					"planetsSize": {
						"min": 0.013732195970593,
						"max": 0.017204613053482,
						"kFactor": 1
					}
				},
				"status": "P",
				"time_modified": "2018-01-25 03:19:01",
				"type": "SINGLE_STAR",
				"affiliation": [
					{
						"id": "1",
						"code": "uee",
						"color": "#48bbd4",
						"name": "UEE",
						"membership.id": "700"
					}
				],
				"celestial_objects": [
					{
						"id": "2101",
						"age": "0.00000000",
						"appearance": "DEFAULT",
						"axial_tilt": "0.00000000",
						"code": "ELYSIUM.JUMPPOINTS.LEIR",
						"description": "Jump Point",
						"designation": "Elysium - Leir",
						"distance": "1.00000000",
						"fairchanceact": "0",
						"habitable": "0",
						"info_url": null,
						"latitude": "-10.97140000",
						"longitude": "-128.85700000",
						"name": null,
						"orbit_period": null,
						"parent_id": null,
						"sensor_danger": "0",
						"sensor_economy": "0",
						"sensor_population": "0",
						"shader_data": null,
						"show_label": "1",
						"show_orbitlines": "0",
						"size": "0.00000000",
						"subtype_id": null,
						"time_modified": "2015-09-15 14:34:06",
						"type": "JUMPPOINT",
						"subtype": null,
						"affiliation": [],
						"population": []
					},
					{
						"id": "2102",
						"age": "0.00000000",
						"appearance": "DEFAULT",
						"axial_tilt": "0.00000000",
						"code": "ELYSIUM.JUMPPOINTS.VANGUARD",
						"description": "Jump Point",
						"designation": "Elysium - Vanguard",
						"distance": "1.00000000",
						"fairchanceact": "0",
						"habitable": "0",
						"info_url": null,
						"latitude": "5.66960000",
						"longitude": "5.97090000",
						"name": null,
						"orbit_period": null,
						"parent_id": null,
						"sensor_danger": "0",
						"sensor_economy": "0",
						"sensor_population": "0",
						"shader_data": null,
						"show_label": "1",
						"show_orbitlines": "0",
						"size": "0.00000000",
						"subtype_id": null,
						"time_modified": "2015-09-15 14:34:06",
						"type": "JUMPPOINT",
						"subtype": null,
						"affiliation": [],
						"population": []
					},
					{
						"id": "2103",
						"age": "0.00000000",
						"appearance": "DEFAULT",
						"axial_tilt": "0.00000000",
						"code": "ELYSIUM.JUMPPOINTS.CENTAURI",
						"description": "Jump Point",
						"designation": "Elysium - Centauri",
						"distance": "1.00000000",
						"fairchanceact": "0",
						"habitable": "0",
						"info_url": null,
						"latitude": "21.54560000",
						"longitude": "-90.81750000",
						"name": null,
						"orbit_period": null,
						"parent_id": null,
						"sensor_danger": "0",
						"sensor_economy": "0",
						"sensor_population": "0",
						"shader_data": null,
						"show_label": "1",
						"show_orbitlines": "0",
						"size": "0.00000000",
						"subtype_id": null,
						"time_modified": "2015-09-15 14:34:06",
						"type": "JUMPPOINT",
						"subtype": null,
						"affiliation": [],
						"population": []
					},
					{
						"id": "2104",
						"age": "0.00000000",
						"appearance": "DEFAULT",
						"axial_tilt": "0.00000000",
						"code": "ELYSIUM.JUMPPOINTS.IDRIS",
						"description": "Jump Point",
						"designation": "Elysium - Idris",
						"distance": "1.00000000",
						"fairchanceact": "0",
						"habitable": "0",
						"info_url": null,
						"latitude": "7.78980000",
						"longitude": "113.35600000",
						"name": null,
						"orbit_period": null,
						"parent_id": null,
						"sensor_danger": "0",
						"sensor_economy": "0",
						"sensor_population": "0",
						"shader_data": null,
						"show_label": "1",
						"show_orbitlines": "0",
						"size": "0.00000000",
						"subtype_id": null,
						"time_modified": "2015-09-15 14:34:06",
						"type": "JUMPPOINT",
						"subtype": null,
						"affiliation": [],
						"population": []
					},
					{
						"id": "2105",
						"age": "0.00000000",
						"appearance": "DEFAULT",
						"axial_tilt": "0.00000000",
						"code": "ELYSIUM.STARS.ELYSIUM",
						"description": null,
						"designation": "Elysium",
						"distance": "0.00000000",
						"fairchanceact": "0",
						"habitable": null,
						"info_url": null,
						"latitude": "0.00000000",
						"longitude": "0.00000000",
						"name": null,
						"orbit_period": "-1.00000000",
						"parent_id": null,
						"sensor_danger": "0",
						"sensor_economy": "0",
						"sensor_population": "0",
						"shader_data": {
							"sun": {
								"color1": "#fff7d9",
								"color2": "rgb(205,90,26)",
								"flare1": 0.265,
								"flare2": 0.5,
								"flare3": 0.265,
								"flare4": 0.10522476008755,
								"flare5": 0.86518136071983,
								"flare6": 0.1,
								"sphere": 0.56119872046692,
								"texture": 1,
								"corona": 0.65473184054474,
								"glow": 0.5,
								"alpha": 1,
								"rotation1": 0.6,
								"rotation2": 0.6,
								"map": "7",
								"iterations": 0,
								"scaleMin": 1,
								"scaleMax": 1,
								"scalePeriod": 1
							},
							"radius": 0.03,
							"orbitalMin": 1,
							"orbitalMax": 5,
							"orbitalFactor": 1
						},
						"show_label": "1",
						"show_orbitlines": "0",
						"size": "801563.16456000",
						"subtype_id": "61",
						"time_modified": "2015-10-10 00:08:05",
						"type": "STAR",
						"subtype": {
							"id": "61",
							"name": "Main Sequence-Dwarf-F",
							"type": "STAR"
						},
						"affiliation": [],
						"population": []
					},
					{
						"id": "2455",
						"age": null,
						"appearance": "PLANET_GAS",
						"axial_tilt": null,
						"code": "ELYSIUM.PLANET.ELYSIUMI",
						"description": "A rare example of a gas giant that formed in the outskirts of the system and migrated to its current orbit very close to the star.\n",
						"designation": "Elysium I",
						"distance": "0.07000000",
						"fairchanceact": null,
						"habitable": null,
						"info_url": null,
						"latitude": null,
						"longitude": "35.27897400",
						"name": null,
						"orbit_period": "10.46000000",
						"parent_id": "2105",
						"sensor_danger": "1",
						"sensor_economy": "1",
						"sensor_population": "1",
						"shader_data": null,
						"show_label": "1",
						"show_orbitlines": "1",
						"size": "46181.00000000",
						"subtype_id": "53",
						"time_modified": "2018-01-25 03:17:36",
						"type": "PLANET",
						"subtype": {
							"id": "53",
							"name": "Puffy Planet",
							"type": "PLANET"
						},
						"affiliation": [
							{
								"id": "1",
								"code": "uee",
								"color": "#48bbd4",
								"name": "UEE",
								"membership.id": "2838"
							}
						],
						"population": [],
						"texture": {
							"slug": "8x8wvjk711ohj",
							"source": "https://robertsspaceindustries.com/media/8x8wvjk711ohjr/source/Planet_Gas.jpg",
							"images": {
								"post": "https://robertsspaceindustries.com/media/8x8wvjk711ohjr/post/Planet_Gas.jpg",
								"product_thumb_large": "https://robertsspaceindustries.com/media/8x8wvjk711ohjr/product_thumb_large/Planet_Gas.jpg",
								"subscribers_vault_thumbnail": "https://robertsspaceindustries.com/media/8x8wvjk711ohjr/subscribers_vault_thumbnail/Planet_Gas.jpg"
							}
						}
					},
					{
						"id": "2456",
						"age": null,
						"appearance": "PLANET_BROWN",
						"axial_tilt": null,
						"code": "ELYSIUM.PLANET.ELYSIUMII",
						"description": "An uninhabited rock covered in deep impact craters. Scientists speculate that the planet was hit by a roaming asteroid. Tevarin historians have not contributed to this discussion.\n",
						"designation": "Elysium II",
						"distance": "0.78000000",
						"fairchanceact": null,
						"habitable": null,
						"info_url": null,
						"latitude": null,
						"longitude": "124.26460000",
						"name": null,
						"orbit_period": "153.74000000",
						"parent_id": "2105",
						"sensor_danger": "4",
						"sensor_economy": "2",
						"sensor_population": "1",
						"shader_data": null,
						"show_label": "1",
						"show_orbitlines": "1",
						"size": "7320.00000000",
						"subtype_id": "19",
						"time_modified": "2018-01-25 03:17:50",
						"type": "PLANET",
						"subtype": {
							"id": "19",
							"name": "Coreless Planet",
							"type": "PLANET"
						},
						"affiliation": [
							{
								"id": "1",
								"code": "uee",
								"color": "#48bbd4",
								"name": "UEE",
								"membership.id": "2839"
							}
						],
						"population": [],
						"texture": {
							"slug": "jnd5qqer9z13g",
							"source": "https://robertsspaceindustries.com/media/jnd5qqer9z13gr/source/Planet_Rocky.jpg",
							"images": {
								"post": "https://robertsspaceindustries.com/media/jnd5qqer9z13gr/post/Planet_Rocky.jpg",
								"product_thumb_large": "https://robertsspaceindustries.com/media/jnd5qqer9z13gr/product_thumb_large/Planet_Rocky.jpg",
								"subscribers_vault_thumbnail": "https://robertsspaceindustries.com/media/jnd5qqer9z13gr/subscribers_vault_thumbnail/Planet_Rocky.jpg"
							}
						}
					},
					{
						"id": "2457",
						"age": null,
						"appearance": "PLANET_BROWN",
						"axial_tilt": null,
						"code": "ELYSIUM.PLANET.ELYSIUMIIIVOSCA",
						"description": "A sprawling arid desert, the surface of Vosca is a merciless environment. Inhabitants constructed the large arcology of Reza\u2019s Landing to shield themselves from the raging sandstorms.\n",
						"designation": "Elysium III",
						"distance": "1.64000000",
						"fairchanceact": null,
						"habitable": "1",
						"info_url": null,
						"latitude": null,
						"longitude": "265.15400000",
						"name": "Vosca",
						"orbit_period": "434.83000000",
						"parent_id": "2105",
						"sensor_danger": "4",
						"sensor_economy": "4",
						"sensor_population": "3",
						"shader_data": null,
						"show_label": "1",
						"show_orbitlines": "1",
						"size": "3786.00000000",
						"subtype_id": "56",
						"time_modified": "2018-01-25 03:18:04",
						"type": "PLANET",
						"subtype": {
							"id": "56",
							"name": "Desert Planet",
							"type": "PLANET"
						},
						"affiliation": [
							{
								"id": "1",
								"code": "uee",
								"color": "#48bbd4",
								"name": "UEE",
								"membership.id": "2840"
							}
						],
						"population": [],
						"texture": {
							"slug": "spa7em2nu5nja",
							"source": "https://robertsspaceindustries.com/media/spa7em2nu5njar/source/Planet_Desert.jpg",
							"images": {
								"post": "https://robertsspaceindustries.com/media/spa7em2nu5njar/post/Planet_Desert.jpg",
								"product_thumb_large": "https://robertsspaceindustries.com/media/spa7em2nu5njar/product_thumb_large/Planet_Desert.jpg",
								"subscribers_vault_thumbnail": "https://robertsspaceindustries.com/media/spa7em2nu5njar/subscribers_vault_thumbnail/Planet_Desert.jpg"
							}
						}
					},
					{
						"id": "2458",
						"age": null,
						"appearance": "PLANET_GREEN",
						"axial_tilt": null,
						"code": "ELYSIUM.PLANETELYSIUMIVJALAN",
						"description": "The former Tevarin homeworld of Kaleeth, Jalan is a beautiful alien world, known for its fields of stunning and bizarre rock formations. The planet still maintains some of the oldest Tevarin structures that managed to survive both wars. A handful of them (including a Rijoran Temple) are located in Gemma, the capital city on Jalan.\n",
						"designation": "Elysium IV",
						"distance": "1.72200000",
						"fairchanceact": null,
						"habitable": "1",
						"info_url": null,
						"latitude": null,
						"longitude": "245.45400000",
						"name": "Jalan",
						"orbit_period": "798.84000000",
						"parent_id": "2105",
						"sensor_danger": "3",
						"sensor_economy": "6",
						"sensor_population": "5",
						"shader_data": null,
						"show_label": "1",
						"show_orbitlines": "1",
						"size": "3348.00000000",
						"subtype_id": "55",
						"time_modified": "2018-01-25 03:18:18",
						"type": "PLANET",
						"subtype": {
							"id": "55",
							"name": "Terrestrial Rocky",
							"type": "PLANET"
						},
						"affiliation": [
							{
								"id": "1",
								"code": "uee",
								"color": "#48bbd4",
								"name": "UEE",
								"membership.id": "2841"
							}
						],
						"population": [],
						"texture": {
							"slug": "duxhoei3b7nnm",
							"source": "https://robertsspaceindustries.com/media/duxhoei3b7nnmr/source/Planet_EarthLike.jpg",
							"images": {
								"post": "https://robertsspaceindustries.com/media/duxhoei3b7nnmr/post/Planet_EarthLike.jpg",
								"product_thumb_large": "https://robertsspaceindustries.com/media/duxhoei3b7nnmr/product_thumb_large/Planet_EarthLike.jpg",
								"subscribers_vault_thumbnail": "https://robertsspaceindustries.com/media/duxhoei3b7nnmr/subscribers_vault_thumbnail/Planet_EarthLike.jpg"
							}
						}
					},
					{
						"id": "2459",
						"age": null,
						"appearance": "PLANET_BLUE",
						"axial_tilt": null,
						"code": "ELYSIUM.PLANET.ELYSIUMV",
						"description": "A distant, dead planet on a long orbit around the star.",
						"designation": "Elysium V",
						"distance": "9.31000000",
						"fairchanceact": null,
						"habitable": null,
						"info_url": null,
						"latitude": null,
						"longitude": "12.56900000",
						"name": null,
						"orbit_period": "14794.77000000",
						"parent_id": "2105",
						"sensor_danger": "3",
						"sensor_economy": "2",
						"sensor_population": "1",
						"shader_data": null,
						"show_label": "1",
						"show_orbitlines": "1",
						"size": "924.00000000",
						"subtype_id": "25",
						"time_modified": "2018-01-25 03:18:35",
						"type": "PLANET",
						"subtype": {
							"id": "25",
							"name": "Ice Giant",
							"type": "PLANET"
						},
						"affiliation": [
							{
								"id": "1",
								"code": "uee",
								"color": "#48bbd4",
								"name": "UEE",
								"membership.id": "2842"
							}
						],
						"population": [],
						"texture": {
							"slug": "j52x7qoth74yi",
							"source": "https://robertsspaceindustries.com/media/j52x7qoth74yir/source/Planet_Ice.jpg",
							"images": {
								"post": "https://robertsspaceindustries.com/media/j52x7qoth74yir/post/Planet_Ice.jpg",
								"product_thumb_large": "https://robertsspaceindustries.com/media/j52x7qoth74yir/product_thumb_large/Planet_Ice.jpg",
								"subscribers_vault_thumbnail": "https://robertsspaceindustries.com/media/j52x7qoth74yir/subscribers_vault_thumbnail/Planet_Ice.jpg"
							}
						}
					}
				],
				"aggregated_size": "9.31000000",
				"aggregated_population": 7.94,
				"aggregated_economy": 1.74,
				"aggregated_danger": 0
			}
		]
	}
}