{
	"success": 1,
	"code": "OK",
	"msg": "OK",
	"data": {
		"rowcount": 1,
		"totalrows": 1,
		"estimatedrows": false,
		"pagesize": 0,
		"pagecount": null,
		"page": 1,
		"offset": 0,
		"startrow": 0,
		"resultset": [
			{
				"id": "355",
				"code": "SOL",
				"description": "The birthplace of Humanity and capital of the Empire. The Imperator, Senate and many other major UEE institutions are based on Earth (Sol III). Among the many historical milestones that the system can lay claim to is the first ever terraformed planet, Mars (Sol IV).",
				"frost_line": "5.00000000",
				"habitable_zone_inner": "0.90000000",
				"habitable_zone_outer": "3.00000000",
				"info_url": null,
				"name": "Sol",
				"position_x": "0.00000000",
				"position_y": "0.00000000",
				"position_z": "0.00000000",
				"shader_data": {
					"lightColor": "#ffffff",
					"starfield": {
						"radius": 95,
						"count": 2000,
						"sizeMin": 1,
						"sizeMax": 1,
						"color1": "rgb(128,128,128)",
						"color2": "rgb(100,100,100)"
					},
					"planetsSize": {
						"min": 0.03,
						"max": 0.03,
						"kFactor": 1
					}
				},
				"status": "P",
				"time_modified": "2015-10-10 14:09:45",
				"type": "SINGLE_STAR",
				"affiliation": [
					{
						"id": "1",
						"code": "uee",
						"color": "#48bbd4",
						"name": "UEE",
						"membership.id": "467"
					}
				],
				"celestial_objects": [
					{
						"id": "2019",
						"age": "0.00000000",
						"appearance": "DEFAULT",
						"axial_tilt": "0.00000000",
						"code": "SOL.JUMPPOINTS.DAVIEN",
						"description": "Jump Point",
						"designation": "Sol - Davien",
						"distance": "16.30000000",
						"fairchanceact": null,
						"habitable": null,
						"info_url": null,
						"latitude": "25.28630000",
						"longitude": "-128.96200000",
						"name": null,
						"orbit_period": null,
						"parent_id": null,
						"sensor_danger": "0",
						"sensor_economy": "0",
						"sensor_population": "0",
						"shader_data": null,
						"show_label": "1",
						"show_orbitlines": null,
						"size": "0.00000000",
						"subtype_id": null,
						"time_modified": "2015-10-09 17:20:47",
						"type": "JUMPPOINT",
						"subtype": null,
						"affiliation": [],
						"population": []
					},
					{
						"id": "2021",
						"age": "0.00000000",
						"appearance": "DEFAULT",
						"axial_tilt": "0.00000000",
						"code": "SOL.JUMPPOINTS.CROSHAW",
						"description": "Jump Point",
						"designation": "Sol - Croshaw",
						"distance": "51.00000000",
						"fairchanceact": null,
						"habitable": null,
						"info_url": null,
						"latitude": "-4.19421000",
						"longitude": "87.21810000",
						"name": null,
						"orbit_period": null,
						"parent_id": null,
						"sensor_danger": "0",
						"sensor_economy": "0",
						"sensor_population": "0",
						"shader_data": null,
						"show_label": "1",
						"show_orbitlines": null,
						"size": "0.00000000",
						"subtype_id": null,
						"time_modified": "2015-10-09 17:20:49",
						"type": "JUMPPOINT",
						"subtype": null,
						"affiliation": [],
						"population": []
					},
					{
						"id": "2023",
						"age": "4.60000000",
						"appearance": "DEFAULT",
						"axial_tilt": "0.00000000",
						"code": "SOL.STARS.SOL",
						"description": null,
						"designation": "Sol",
						"distance": "0.00000000",
						"fairchanceact": "0",
						"habitable": null,
						"info_url": null,
						"latitude": "0.00000000",
						"longitude": "0.00000000",
						"name": null,
						"orbit_period": null,
						"parent_id": null,
						"sensor_danger": "0",
						"sensor_economy": "0",
						"sensor_population": "0",
						"shader_data": {
							"orbitalMin": 1,
							"orbitalMax": 5,
							"orbitalFactor": 1,
							"sun": {
								"color1": "rgb(205,166,77)",
								"color2": "rgb(205,90,26)",
								"flare1": 0.265,
								"flare2": 0.5,
								"flare3": 0.265,
								"flare4": 0.5,
								"flare5": 0.5,
								"flare6": 0.1,
								"sphere": 1,
								"texture": 1,
								"corona": 1,
								"glow": 0.5,
								"alpha": 1,
								"rotation1": 0.6,
								"rotation2": 0.6,
								"map": 0,
								"iterations": 0,
								"scaleMin": 1,
								"scaleMax": 1,
								"scalePeriod": 1
							},
							"radius": 0.06
						},
						"show_label": "1",
						"show_orbitlines": "0",
						"size": "1.00000000",
						"subtype_id": "59",
						"time_modified": "2015-10-10 01:21:37",
						"type": "STAR",
						"subtype": {
							"id": "59",
							"name": "Main Sequence-Dwarf-G",
							"type": "STAR"
						},
						"affiliation": [],
						"population": []
					},
					{
						"id": "2024",
						"age": "0.00000000",
						"appearance": "PLANET_BROWN",
						"axial_tilt": "0.00000000",
						"code": "SOL.PLANETS.MERCURY",
						"description": "Due to an orbital eccentricity, this small planet experiences the greatest temperature variations of any planet in the system.",
						"designation": "Sol I",
						"distance": "0.46669700",
						"fairchanceact": null,
						"habitable": null,
						"info_url": null,
						"latitude": "-3.61006000",
						"longitude": "59.39330000",
						"name": "Mercury",
						"orbit_period": "87.96900000",
						"parent_id": "2023",
						"sensor_danger": "2",
						"sensor_economy": "1",
						"sensor_population": "1",
						"shader_data": null,
						"show_label": "1",
						"show_orbitlines": "1",
						"size": "2439.70000000",
						"subtype_id": "27",
						"time_modified": "2015-10-09 14:13:09",
						"type": "PLANET",
						"subtype": {
							"id": "27",
							"name": "Iron Planet",
							"type": "PLANET"
						},
						"affiliation": [
							{
								"id": "1",
								"code": "uee",
								"color": "#48bbd4",
								"name": "UEE",
								"membership.id": "2278"
							}
						],
						"population": [],
						"texture": {
							"slug": "vx5nehwypz25d",
							"source": "https://robertsspaceindustries.com/media/vx5nehwypz25dr/source/Mercury.jpg",
							"images": {
								"post": "https://robertsspaceindustries.com/media/vx5nehwypz25dr/post/Mercury.jpg",
								"product_thumb_large": "https://robertsspaceindustries.com/media/vx5nehwypz25dr/product_thumb_large/Mercury.jpg",
								"subscribers_vault_thumbnail": "https://robertsspaceindustries.com/media/vx5nehwypz25dr/subscribers_vault_thumbnail/Mercury.jpg"
							}
						}
					},
					{
						"id": "2025",
						"age": "0.00000000",
						"appearance": "PLANET_BROWN",
						"axial_tilt": "0.00000000",
						"code": "SOL.PLANETS.VENUS",
						"description": "Venus\u2019s atmosphere is almost entirely composed of carbon dioxide, which makes it the hottest planet in the Sol System.",
						"designation": "Sol II",
						"distance": "0.72821300",
						"fairchanceact": null,
						"habitable": null,
						"info_url": null,
						"latitude": "3.34633000",
						"longitude": "169.76000000",
						"name": "Venus",
						"orbit_period": "224.70100000",
						"parent_id": "2023",
						"sensor_danger": "3",
						"sensor_economy": "1",
						"sensor_population": "1",
						"shader_data": null,
						"show_label": "1",
						"show_orbitlines": "1",
						"size": "6051.80000000",
						"subtype_id": "20",
						"time_modified": "2015-10-08 21:19:46",
						"type": "PLANET",
						"subtype": {
							"id": "20",
							"name": "Smog Planet",
							"type": "PLANET"
						},
						"affiliation": [
							{
								"id": "1",
								"code": "uee",
								"color": "#48bbd4",
								"name": "UEE",
								"membership.id": "2158"
							}
						],
						"population": [],
						"texture": {
							"slug": "j8qfxa304mrco",
							"source": "https://robertsspaceindustries.com/media/j8qfxa304mrcor/source/Planet_Venus.jpg",
							"images": {
								"post": "https://robertsspaceindustries.com/media/j8qfxa304mrcor/post/Planet_Venus.jpg",
								"product_thumb_large": "https://robertsspaceindustries.com/media/j8qfxa304mrcor/product_thumb_large/Planet_Venus.jpg",
								"subscribers_vault_thumbnail": "https://robertsspaceindustries.com/media/j8qfxa304mrcor/subscribers_vault_thumbnail/Planet_Venus.jpg"
							}
						}
					},
					{
						"id": "2026",
						"age": "0.00000000",
						"appearance": "DEFAULT",
						"axial_tilt": "0.00000000",
						"code": "SOL.PLANETS.EARTH",
						"description": "Humanity\u2019s homeworld and namesake of the United Empire of Earth. It is the center of the UEE political machine and a focal point in the Empire\u2019s commerce and culture. Centuries of habitation have stripped the planet of its natural resources resulting in a heavy dependence on imports for the billions that live here. ",
						"designation": "Sol III",
						"distance": "1.00000000",
						"fairchanceact": null,
						"habitable": "1",
						"info_url": null,
						"latitude": "0.00000000",
						"longitude": "74.68260000",
						"name": "Earth",
						"orbit_period": "365.25600000",
						"parent_id": "2023",
						"sensor_danger": "3",
						"sensor_economy": "10",
						"sensor_population": "7",
						"shader_data": null,
						"show_label": "1",
						"show_orbitlines": "1",
						"size": "6371.00000000",
						"subtype_id": "55",
						"time_modified": "2016-06-27 18:07:36",
						"type": "PLANET",
						"subtype": {
							"id": "55",
							"name": "Terrestrial Rocky",
							"type": "PLANET"
						},
						"affiliation": [
							{
								"id": "1",
								"code": "uee",
								"color": "#48bbd4",
								"name": "UEE",
								"membership.id": "2711"
							}
						],
						"population": [],
						"thumbnail": {
							"slug": "722i0s9ojuf58",
							"source": "https://robertsspaceindustries.com/media/722i0s9ojuf58r/source/Earthjp-Nyc.png",
							"images": {
								"post": "https://robertsspaceindustries.com/media/722i0s9ojuf58r/post/Earthjp-Nyc.png",
								"product_thumb_large": "https://robertsspaceindustries.com/media/722i0s9ojuf58r/product_thumb_large/Earthjp-Nyc.png",
								"subscribers_vault_thumbnail": "https://robertsspaceindustries.com/media/722i0s9ojuf58r/subscribers_vault_thumbnail/Earthjp-Nyc.png"
							}
						},
						"texture": {
							"slug": "5dvd8cognsxbg",
							"source": "https://robertsspaceindustries.com/media/5dvd8cognsxbgr/source/Planet_Earth512.jpg",
							"images": {
								"post": "https://robertsspaceindustries.com/media/5dvd8cognsxbgr/post/Planet_Earth512.jpg",
								"product_thumb_large": "https://robertsspaceindustries.com/media/5dvd8cognsxbgr/product_thumb_large/Planet_Earth512.jpg",
								"subscribers_vault_thumbnail": "https://robertsspaceindustries.com/media/5dvd8cognsxbgr/subscribers_vault_thumbnail/Planet_Earth512.jpg"
							}
						}
					},
					{
						"id": "2027",
						"age": "0.00000000",
						"appearance": "PLANET_BROWN",
						"axial_tilt": "0.00000000",
						"code": "SOL.PLANETS.MARS",
						"description": "A prosperous and populous planet, Mars was the Empire\u2019s first successfully terraformed planet. The process was marred by what is today known as the Mars Tragedy when a terraforming disaster killed 4,876 people in 2125.",
						"designation": "Sol IV",
						"distance": "1.52400000",
						"fairchanceact": null,
						"habitable": "1",
						"info_url": null,
						"latitude": "-1.77345000",
						"longitude": "16.63730000",
						"name": "Mars",
						"orbit_period": "687.18000000",
						"parent_id": "2023",
						"sensor_danger": "4",
						"sensor_economy": "8",
						"sensor_population": "6",
						"shader_data": null,
						"show_label": "1",
						"show_orbitlines": "1",
						"size": "3389.50000000",
						"subtype_id": "56",
						"time_modified": "2015-10-08 23:45:19",
						"type": "PLANET",
						"subtype": {
							"id": "56",
							"name": "Desert Planet",
							"type": "PLANET"
						},
						"affiliation": [
							{
								"id": "1",
								"code": "uee",
								"color": "#48bbd4",
								"name": "UEE",
								"membership.id": "2243"
							}
						],
						"population": [],
						"texture": {
							"slug": "7wes0jfwwl1bc",
							"source": "https://robertsspaceindustries.com/media/7wes0jfwwl1bcr/source/Planet_Mars.jpg",
							"images": {
								"post": "https://robertsspaceindustries.com/media/7wes0jfwwl1bcr/post/Planet_Mars.jpg",
								"product_thumb_large": "https://robertsspaceindustries.com/media/7wes0jfwwl1bcr/product_thumb_large/Planet_Mars.jpg",
								"subscribers_vault_thumbnail": "https://robertsspaceindustries.com/media/7wes0jfwwl1bcr/subscribers_vault_thumbnail/Planet_Mars.jpg"
							}
						}
					},
					{
						"id": "2028",
						"age": "0.00000000",
						"appearance": "PLANET_BROWN",
						"axial_tilt": "0.00000000",
						"code": "SOL.PLANETS.JUPITER",
						"description": "This gas giant is the largest planet in the Sol System.  ",
						"designation": "Sol V",
						"distance": "5.20400000",
						"fairchanceact": null,
						"habitable": null,
						"info_url": null,
						"latitude": "-0.94877800",
						"longitude": "43.46780000",
						"name": "Jupiter",
						"orbit_period": "4332.59000000",
						"parent_id": "2023",
						"sensor_danger": "3",
						"sensor_economy": "2",
						"sensor_population": "1",
						"shader_data": {
							"orbitalMin": 1,
							"orbitalMax": 5,
							"orbitalFactor": 1,
							"ring": {
								"color1": "#4d2400",
								"color2": "#696969",
								"radius1": 0.84179808070038,
								"radius2": 1
							},
							"highlight": {
								"color1": "rgb(255,255,255)",
								"color2": "rgb(255,255,255)",
								"alpha": 1,
								"atmosphere1": 0.5,
								"atmosphere2": 0.5,
								"atmosphere3": 0.5,
								"scaleMin": 1,
								"scaleMax": 1,
								"scalePeriod": 1
							},
							"orbitalColor": "rgb(26,86,124)",
							"orbitalHighlightColor": "rgb(128,128,255)"
						},
						"show_label": "1",
						"show_orbitlines": "1",
						"size": "69911.00000000",
						"subtype_id": "23",
						"time_modified": "2015-10-13 21:24:17",
						"type": "PLANET",
						"subtype": {
							"id": "23",
							"name": "Gas Giant",
							"type": "PLANET"
						},
						"affiliation": [
							{
								"id": "1",
								"code": "uee",
								"color": "#48bbd4",
								"name": "UEE",
								"membership.id": "2534"
							}
						],
						"population": [],
						"texture": {
							"slug": "yyxagrxfet5z8",
							"source": "https://robertsspaceindustries.com/media/yyxagrxfet5z8r/source/Planet_Jupiter.jpg",
							"images": {
								"post": "https://robertsspaceindustries.com/media/yyxagrxfet5z8r/post/Planet_Jupiter.jpg",
								"product_thumb_large": "https://robertsspaceindustries.com/media/yyxagrxfet5z8r/product_thumb_large/Planet_Jupiter.jpg",
								"subscribers_vault_thumbnail": "https://robertsspaceindustries.com/media/yyxagrxfet5z8r/subscribers_vault_thumbnail/Planet_Jupiter.jpg"
							}
						}
					},
					{
						"id": "2029",
						"age": "0.00000000",
						"appearance": "PLANET_BROWN",
						"axial_tilt": "0.00000000",
						"code": "SOL.PLANETS.SATURN",
						"description": "A gas giant best known for its set of planetary rings.",
						"designation": "Sol VI",
						"distance": "10.11600000",
						"fairchanceact": null,
						"habitable": null,
						"info_url": null,
						"latitude": "1.72675000",
						"longitude": "-133.96800000",
						"name": "Saturn",
						"orbit_period": "10759.20000000",
						"parent_id": "2023",
						"sensor_danger": "3",
						"sensor_economy": "1",
						"sensor_population": "1",
						"shader_data": {
							"orbitalMin": 2.331658810645,
							"orbitalMax": 4.7551561599552,
							"orbitalFactor": 1,
							"ring": {
								"color1": "#73558e",
								"color2": "#2a7db6",
								"radius1": 0.4676656003891,
								"radius2": 0.98209776081711,
								"speed": 0.75
							},
							"highlight": {
								"color1": "rgb(255,255,255)",
								"color2": "rgb(255,255,255)",
								"alpha": 1,
								"atmosphere1": 0.5,
								"atmosphere2": 0.5,
								"atmosphere3": 0.5,
								"scaleMin": 1,
								"scaleMax": 1,
								"scalePeriod": 1
							},
							"orbitalColor": "rgb(26,86,124)",
							"orbitalHighlightColor": "rgb(128,128,255)"
						},
						"show_label": "1",
						"show_orbitlines": "1",
						"size": "58232.00000000",
						"subtype_id": "23",
						"time_modified": "2015-10-13 21:26:48",
						"type": "PLANET",
						"subtype": {
							"id": "23",
							"name": "Gas Giant",
							"type": "PLANET"
						},
						"affiliation": [
							{
								"id": "1",
								"code": "uee",
								"color": "#48bbd4",
								"name": "UEE",
								"membership.id": "2536"
							}
						],
						"population": [],
						"texture": {
							"slug": "ps9wli4v169nb",
							"source": "https://robertsspaceindustries.com/media/ps9wli4v169nbr/source/Planet_Saturne.jpg",
							"images": {
								"post": "https://robertsspaceindustries.com/media/ps9wli4v169nbr/post/Planet_Saturne.jpg",
								"product_thumb_large": "https://robertsspaceindustries.com/media/ps9wli4v169nbr/product_thumb_large/Planet_Saturne.jpg",
								"subscribers_vault_thumbnail": "https://robertsspaceindustries.com/media/ps9wli4v169nbr/subscribers_vault_thumbnail/Planet_Saturne.jpg"
							}
						}
					},
					{
						"id": "2030",
						"age": "0.00000000",
						"appearance": "DEFAULT",
						"axial_tilt": "97.77000000",
						"code": "SOL.PLANETS.URANUS",
						"description": "This ice giant has an unusual lopsided magnetic field due to a dramatic tilt of its axis that places its north and south poles where most other planets have their equator.",
						"designation": "Sol VII",
						"distance": "20.08330000",
						"fairchanceact": null,
						"habitable": null,
						"info_url": null,
						"latitude": "0.73716400",
						"longitude": "162.57400000",
						"name": "Uranus",
						"orbit_period": "30799.10000000",
						"parent_id": "2023",
						"sensor_danger": "4",
						"sensor_economy": "2",
						"sensor_population": "1",
						"shader_data": {
							"orbitalMin": 1,
							"orbitalMax": 5,
							"orbitalFactor": 1,
							"ring": {
								"color1": "#000000",
								"color2": "#898989",
								"radius1": 0.65473184054474,
								"radius2": 1,
								"speed": 0.75,
								"extraDensity": 0.01,
								"borderFading": 0.2
							},
							"highlight": {
								"color1": "rgb(255,255,255)",
								"color2": "rgb(255,255,255)",
								"alpha": 1,
								"atmosphere1": 0.5,
								"atmosphere2": 0.5,
								"atmosphere3": 0.5,
								"scaleMin": 1,
								"scaleMax": 1,
								"scalePeriod": 1
							},
							"orbitalColor": "rgb(26,86,124)",
							"orbitalHighlightColor": "rgb(128,128,255)"
						},
						"show_label": "1",
						"show_orbitlines": "1",
						"size": "25362.00000000",
						"subtype_id": "25",
						"time_modified": "2015-10-09 22:21:10",
						"type": "PLANET",
						"subtype": {
							"id": "25",
							"name": "Ice Giant",
							"type": "PLANET"
						},
						"affiliation": [
							{
								"id": "1",
								"code": "uee",
								"color": "#48bbd4",
								"name": "UEE",
								"membership.id": "2380"
							}
						],
						"population": [],
						"texture": {
							"slug": "0jumx7t0c3ytz",
							"source": "https://robertsspaceindustries.com/media/0jumx7t0c3ytzr/source/Planet_Uranus.jpg",
							"images": {
								"post": "https://robertsspaceindustries.com/media/0jumx7t0c3ytzr/post/Planet_Uranus.jpg",
								"product_thumb_large": "https://robertsspaceindustries.com/media/0jumx7t0c3ytzr/product_thumb_large/Planet_Uranus.jpg",
								"subscribers_vault_thumbnail": "https://robertsspaceindustries.com/media/0jumx7t0c3ytzr/subscribers_vault_thumbnail/Planet_Uranus.jpg"
							}
						}
					},
					{
						"id": "2031",
						"age": "0.00000000",
						"appearance": "PLANET_BLUE",
						"axial_tilt": "0.00000000",
						"code": "SOL.PLANETS.NEPTUNE",
						"description": "An ice giant whose differential rotation contributes to it having the strongest winds in the Sol System.",
						"designation": "Sol VIII",
						"distance": "30.44130000",
						"fairchanceact": null,
						"habitable": null,
						"info_url": null,
						"latitude": "1.02226000",
						"longitude": "125.31000000",
						"name": "Neptune",
						"orbit_period": "60190.00000000",
						"parent_id": "2023",
						"sensor_danger": "3",
						"sensor_economy": "1",
						"sensor_population": "1",
						"shader_data": {
							"orbitalMin": 1,
							"orbitalMax": 5,
							"orbitalFactor": 1,
							"ring": {
								"color1": "#aaa5a1",
								"color2": "#161615",
								"radius1": 0.6,
								"radius2": 1,
								"speed": 0.75,
								"extraDensity": 0.01,
								"borderFading": 0.2
							},
							"highlight": {
								"color1": "rgb(255,255,255)",
								"color2": "rgb(255,255,255)",
								"alpha": 0.55,
								"atmosphere1": 0.5,
								"atmosphere2": 0.5,
								"atmosphere3": 0.5,
								"scaleMin": 1,
								"scaleMax": 1,
								"scalePeriod": 1
							},
							"orbitalColor": "rgb(26,86,124)",
							"orbitalHighlightColor": "rgb(128,128,255)"
						},
						"show_label": "1",
						"show_orbitlines": "1",
						"size": "24622.00000000",
						"subtype_id": "25",
						"time_modified": "2015-10-09 22:21:55",
						"type": "PLANET",
						"subtype": {
							"id": "25",
							"name": "Ice Giant",
							"type": "PLANET"
						},
						"affiliation": [
							{
								"id": "1",
								"code": "uee",
								"color": "#48bbd4",
								"name": "UEE",
								"membership.id": "2281"
							}
						],
						"population": [],
						"texture": {
							"slug": "94je2ho8w8fbe",
							"source": "https://robertsspaceindustries.com/media/94je2ho8w8fber/source/Planet_Neptune.jpg",
							"images": {
								"post": "https://robertsspaceindustries.com/media/94je2ho8w8fber/post/Planet_Neptune.jpg",
								"product_thumb_large": "https://robertsspaceindustries.com/media/94je2ho8w8fber/product_thumb_large/Planet_Neptune.jpg",
								"subscribers_vault_thumbnail": "https://robertsspaceindustries.com/media/94je2ho8w8fber/subscribers_vault_thumbnail/Planet_Neptune.jpg"
							}
						}
					},
					{
						"id": "2032",
						"age": "0.00000000",
						"appearance": "DEFAULT",
						"axial_tilt": "0.00000000",
						"code": "SOL.PLANETS.PLUTO",
						"description": "This dwarf planet was the first Kuiper Belt object to ever be discovered and is primarily made of ice and rock. ",
						"designation": "Sol IX",
						"distance": "39.50000000",
						"fairchanceact": null,
						"habitable": null,
						"info_url": null,
						"latitude": "13.37350000",
						"longitude": "-133.97300000",
						"name": "Pluto",
						"orbit_period": "90465.00000000",
						"parent_id": "2023",
						"sensor_danger": "2",
						"sensor_economy": "1",
						"sensor_population": "1",
						"shader_data": null,
						"show_label": "1",
						"show_orbitlines": "1",
						"size": "1186.00000000",
						"subtype_id": "21",
						"time_modified": "2015-10-20 19:16:25",
						"type": "PLANET",
						"subtype": {
							"id": "21",
							"name": "Dwarf Planet",
							"type": "PLANET"
						},
						"affiliation": [
							{
								"id": "1",
								"code": "uee",
								"color": "#48bbd4",
								"name": "UEE",
								"membership.id": "2571"
							}
						],
						"population": [],
						"texture": {
							"slug": "pmfkvj1mwmq2z",
							"source": "https://robertsspaceindustries.com/media/pmfkvj1mwmq2zr/source/Planet_Pluto.jpg",
							"images": {
								"post": "https://robertsspaceindustries.com/media/pmfkvj1mwmq2zr/post/Planet_Pluto.jpg",
								"product_thumb_large": "https://robertsspaceindustries.com/media/pmfkvj1mwmq2zr/product_thumb_large/Planet_Pluto.jpg",
								"subscribers_vault_thumbnail": "https://robertsspaceindustries.com/media/pmfkvj1mwmq2zr/subscribers_vault_thumbnail/Planet_Pluto.jpg"
							}
						}
					},
					{
						"id": "2033",
						"age": "0.00000000",
						"appearance": "PLANET_BROWN",
						"axial_tilt": "0.00000000",
						"code": "SOL.PLANETS.LUNA",
						"description": "A large natural satellite that is tidally locked with Earth. The first celestial object Humanity ever visited.",
						"designation": "Sol 3a",
						"distance": "0.00246642",
						"fairchanceact": null,
						"habitable": null,
						"info_url": null,
						"latitude": "3.79789000",
						"longitude": "137.36200000",
						"name": "Luna",
						"orbit_period": "27.32160000",
						"parent_id": "2026",
						"sensor_danger": "0",
						"sensor_economy": "0",
						"sensor_population": "0",
						"shader_data": {
							"orbitalMin": 1,
							"orbitalMax": 5,
							"orbitalFactor": 1,
							"highlight": {
								"color1": "rgb(255,255,255)",
								"color2": "rgb(255,255,255)",
								"alpha": 1,
								"atmosphere1": 0.5,
								"atmosphere2": 0.5,
								"atmosphere3": 0.5,
								"scaleMin": 1,
								"scaleMax": 1,
								"scalePeriod": 1
							},
							"radius": 0.008
						},
						"show_label": null,
						"show_orbitlines": null,
						"size": "1.00000000",
						"subtype_id": "52",
						"time_modified": "2015-10-09 17:25:53",
						"type": "SATELLITE",
						"subtype": {
							"id": "52",
							"name": "Planetary Moon",
							"type": "SATELLITE"
						},
						"affiliation": [],
						"population": [],
						"texture": {
							"slug": "9g2xvstat60bi",
							"source": "https://robertsspaceindustries.com/media/9g2xvstat60bir/source/Planet_Moon.jpg",
							"images": {
								"post": "https://robertsspaceindustries.com/media/9g2xvstat60bir/post/Planet_Moon.jpg",
								"product_thumb_large": "https://robertsspaceindustries.com/media/9g2xvstat60bir/product_thumb_large/Planet_Moon.jpg",
								"subscribers_vault_thumbnail": "https://robertsspaceindustries.com/media/9g2xvstat60bir/subscribers_vault_thumbnail/Planet_Moon.jpg"
							}
						}
					},
					{
						"id": "2034",
						"age": "0.00000000",
						"appearance": "DEFAULT",
						"axial_tilt": "0.00000000",
						"code": "SOL.PLANETS.IO",
						"description": "Thanks to tidal heating, Io experiences extreme geologic activity, making it the driest and most volcanically active object in the Sol System.",
						"designation": "Sol 5a",
						"distance": "0.00281889",
						"fairchanceact": null,
						"habitable": null,
						"info_url": null,
						"latitude": "2.20466000",
						"longitude": "175.44500000",
						"name": "Io",
						"orbit_period": "1.77000000",
						"parent_id": "2028",
						"sensor_danger": "0",
						"sensor_economy": "0",
						"sensor_population": "0",
						"shader_data": {
							"orbitalMin": 1,
							"orbitalMax": 5,
							"orbitalFactor": 1,
							"highlight": {
								"color1": "rgb(255,255,255)",
								"color2": "rgb(255,255,255)",
								"alpha": 1,
								"atmosphere1": 0.5,
								"atmosphere2": 0.5,
								"atmosphere3": 0.5,
								"scaleMin": 1,
								"scaleMax": 1,
								"scalePeriod": 1
							},
							"radius": 0.005
						},
						"show_label": null,
						"show_orbitlines": null,
						"size": "1.00000000",
						"subtype_id": "52",
						"time_modified": "2015-10-09 17:14:32",
						"type": "SATELLITE",
						"subtype": {
							"id": "52",
							"name": "Planetary Moon",
							"type": "SATELLITE"
						},
						"affiliation": [],
						"population": [],
						"texture": {
							"slug": "9g2xvstat60bi",
							"source": "https://robertsspaceindustries.com/media/9g2xvstat60bir/source/Planet_Moon.jpg",
							"images": {
								"post": "https://robertsspaceindustries.com/media/9g2xvstat60bir/post/Planet_Moon.jpg",
								"product_thumb_large": "https://robertsspaceindustries.com/media/9g2xvstat60bir/product_thumb_large/Planet_Moon.jpg",
								"subscribers_vault_thumbnail": "https://robertsspaceindustries.com/media/9g2xvstat60bir/subscribers_vault_thumbnail/Planet_Moon.jpg"
							}
						}
					},
					{
						"id": "2035",
						"age": "0.00000000",
						"appearance": "DEFAULT",
						"axial_tilt": "0.00000000",
						"code": "SOL.PLANETS.EUROPA",
						"description": "Europa's icy surface makes it one of the most reflective moons in the Sol System.",
						"designation": "Sol 5b",
						"distance": "0.00448558",
						"fairchanceact": null,
						"habitable": null,
						"info_url": null,
						"latitude": "0.20010700",
						"longitude": "115.19800000",
						"name": "Europa",
						"orbit_period": "3.55000000",
						"parent_id": "2028",
						"sensor_danger": "0",
						"sensor_economy": "0",
						"sensor_population": "0",
						"shader_data": {
							"orbitalMin": 1,
							"orbitalMax": 5,
							"orbitalFactor": 1,
							"highlight": {
								"color1": "rgb(255,255,255)",
								"color2": "rgb(255,255,255)",
								"alpha": 1,
								"atmosphere1": 0.5,
								"atmosphere2": 0.5,
								"atmosphere3": 0.5,
								"scaleMin": 0.99378940082683,
								"scaleMax": 1,
								"scalePeriod": 1
							},
							"radius": 0.005
						},
						"show_label": null,
						"show_orbitlines": null,
						"size": "1.00000000",
						"subtype_id": "52",
						"time_modified": "2015-10-09 17:14:36",
						"type": "SATELLITE",
						"subtype": {
							"id": "52",
							"name": "Planetary Moon",
							"type": "SATELLITE"
						},
						"affiliation": [],
						"population": [],
						"texture": {
							"slug": "j52x7qoth74yi",
							"source": "https://robertsspaceindustries.com/media/j52x7qoth74yir/source/Planet_Ice.jpg",
							"images": {
								"post": "https://robertsspaceindustries.com/media/j52x7qoth74yir/post/Planet_Ice.jpg",
								"product_thumb_large": "https://robertsspaceindustries.com/media/j52x7qoth74yir/product_thumb_large/Planet_Ice.jpg",
								"subscribers_vault_thumbnail": "https://robertsspaceindustries.com/media/j52x7qoth74yir/subscribers_vault_thumbnail/Planet_Ice.jpg"
							}
						}
					},
					{
						"id": "2036",
						"age": "0.00000000",
						"appearance": "DEFAULT",
						"axial_tilt": "0.00000000",
						"code": "SOL.PLANETS.GANYMEDE",
						"description": "Ganymede is the Sol System\u2019s largest moon and the only one with a magnetosphere. It is bigger than Mercury and only slightly smaller than Mars.",
						"designation": "Sol 5c",
						"distance": "0.00715526",
						"fairchanceact": null,
						"habitable": null,
						"info_url": null,
						"latitude": "-0.15980200",
						"longitude": "36.96460000",
						"name": "Ganymede",
						"orbit_period": "7.15000000",
						"parent_id": "2028",
						"sensor_danger": "0",
						"sensor_economy": "0",
						"sensor_population": "0",
						"shader_data": {
							"orbitalMin": 1,
							"orbitalMax": 5,
							"orbitalFactor": 1,
							"highlight": {
								"color1": "rgb(255,255,255)",
								"color2": "rgb(255,255,255)",
								"alpha": 1,
								"atmosphere1": 0.5,
								"atmosphere2": 0.5,
								"atmosphere3": 0.5,
								"scaleMin": 1,
								"scaleMax": 1,
								"scalePeriod": 1
							},
							"radius": 0.007
						},
						"show_label": null,
						"show_orbitlines": null,
						"size": "1.00000000",
						"subtype_id": "52",
						"time_modified": "2015-10-09 17:15:11",
						"type": "SATELLITE",
						"subtype": {
							"id": "52",
							"name": "Planetary Moon",
							"type": "SATELLITE"
						},
						"affiliation": [],
						"population": [],
						"texture": {
							"slug": "9g2xvstat60bi",
							"source": "https://robertsspaceindustries.com/media/9g2xvstat60bir/source/Planet_Moon.jpg",
							"images": {
								"post": "https://robertsspaceindustries.com/media/9g2xvstat60bir/post/Planet_Moon.jpg",
								"product_thumb_large": "https://robertsspaceindustries.com/media/9g2xvstat60bir/product_thumb_large/Planet_Moon.jpg",
								"subscribers_vault_thumbnail": "https://robertsspaceindustries.com/media/9g2xvstat60bir/subscribers_vault_thumbnail/Planet_Moon.jpg"
							}
						}
					},
					{
						"id": "2037",
						"age": "0.00000000",
						"appearance": "DEFAULT",
						"axial_tilt": "0.00000000",
						"code": "SOL.PLANETS.CALLISTO",
						"description": "The tidally locked surface of Callisto is the oldest and most heavily cratered in Sol. ",
						"designation": "Sol 5d",
						"distance": "0.01258510",
						"fairchanceact": null,
						"habitable": null,
						"info_url": null,
						"latitude": "0.04677470",
						"longitude": "-104.10000000",
						"name": "Callisto",
						"orbit_period": "16.69000000",
						"parent_id": "2028",
						"sensor_danger": "0",
						"sensor_economy": "0",
						"sensor_population": "0",
						"shader_data": {
							"orbitalMin": 1,
							"orbitalMax": 5,
							"orbitalFactor": 1,
							"highlight": {
								"color1": "rgb(255,255,255)",
								"color2": "rgb(255,255,255)",
								"alpha": 1,
								"atmosphere1": 0.5,
								"atmosphere2": 0.5,
								"atmosphere3": 0.5,
								"scaleMin": 1,
								"scaleMax": 1,
								"scalePeriod": 1
							},
							"radius": 0.004
						},
						"show_label": null,
						"show_orbitlines": null,
						"size": "1.00000000",
						"subtype_id": "52",
						"time_modified": "2015-10-13 17:19:27",
						"type": "SATELLITE",
						"subtype": {
							"id": "52",
							"name": "Planetary Moon",
							"type": "SATELLITE"
						},
						"affiliation": [],
						"population": [],
						"texture": {
							"slug": "9g2xvstat60bi",
							"source": "https://robertsspaceindustries.com/media/9g2xvstat60bir/source/Planet_Moon.jpg",
							"images": {
								"post": "https://robertsspaceindustries.com/media/9g2xvstat60bir/post/Planet_Moon.jpg",
								"product_thumb_large": "https://robertsspaceindustries.com/media/9g2xvstat60bir/product_thumb_large/Planet_Moon.jpg",
								"subscribers_vault_thumbnail": "https://robertsspaceindustries.com/media/9g2xvstat60bir/subscribers_vault_thumbnail/Planet_Moon.jpg"
							}
						}
					},
					{
						"id": "2038",
						"age": "0.00000000",
						"appearance": "DEFAULT",
						"axial_tilt": "0.00000000",
						"code": "SOL.BELTS.RINGSOFSATURN",
						"description": "Planetary Ring System",
						"designation": "Rings of Saturn",
						"distance": "0.00077051",
						"fairchanceact": null,
						"habitable": null,
						"info_url": null,
						"latitude": "0.00000000",
						"longitude": "0.00000000",
						"name": null,
						"orbit_period": null,
						"parent_id": "2029",
						"sensor_danger": "0",
						"sensor_economy": "0",
						"sensor_population": "0",
						"shader_data": null,
						"show_label": "1",
						"show_orbitlines": "1",
						"size": "0.00000000",
						"subtype_id": "51",
						"time_modified": "2015-10-08 03:56:40",
						"type": "ASTEROID_BELT",
						"subtype": {
							"id": "51",
							"name": "Planetary Ring",
							"type": "ASTEROID_BELT"
						},
						"affiliation": [],
						"population": []
					},
					{
						"id": "2039",
						"age": "0.00000000",
						"appearance": "DEFAULT",
						"axial_tilt": "0.00000000",
						"code": "SOL.BELTS.JOVIANRINGS",
						"description": "Planetary Ring System",
						"designation": "Jovian Rings",
						"distance": "0.00081900",
						"fairchanceact": null,
						"habitable": null,
						"info_url": null,
						"latitude": "0.00000000",
						"longitude": "0.00000000",
						"name": null,
						"orbit_period": null,
						"parent_id": "2028",
						"sensor_danger": "0",
						"sensor_economy": "0",
						"sensor_population": "0",
						"shader_data": null,
						"show_label": "1",
						"show_orbitlines": "1",
						"size": "0.00000000",
						"subtype_id": "51",
						"time_modified": "2015-10-08 23:56:37",
						"type": "ASTEROID_BELT",
						"subtype": {
							"id": "51",
							"name": "Planetary Ring",
							"type": "ASTEROID_BELT"
						},
						"affiliation": [],
						"population": []
					},
					{
						"id": "2040",
						"age": "0.00000000",
						"appearance": "DEFAULT",
						"axial_tilt": "0.00000000",
						"code": "SOL.BELTS.RINGSOFNEPTUNE",
						"description": "Planetary Ring System",
						"designation": "Rings of Neptune",
						"distance": "0.00028100",
						"fairchanceact": null,
						"habitable": null,
						"info_url": null,
						"latitude": "0.00000000",
						"longitude": "0.00000000",
						"name": null,
						"orbit_period": null,
						"parent_id": "2031",
						"sensor_danger": "0",
						"sensor_economy": "0",
						"sensor_population": "0",
						"shader_data": null,
						"show_label": "1",
						"show_orbitlines": "1",
						"size": "0.00000000",
						"subtype_id": "51",
						"time_modified": "2015-10-08 03:57:01",
						"type": "ASTEROID_BELT",
						"subtype": {
							"id": "51",
							"name": "Planetary Ring",
							"type": "ASTEROID_BELT"
						},
						"affiliation": [],
						"population": []
					},
					{
						"id": "2041",
						"age": "0.00000000",
						"appearance": "DEFAULT",
						"axial_tilt": "0.00000000",
						"code": "SOL.BELTS.RINGSOFURANUS",
						"description": "Planetary Ring System",
						"designation": "Rings of Uranus",
						"distance": "0.00023400",
						"fairchanceact": null,
						"habitable": null,
						"info_url": null,
						"latitude": "0.00000000",
						"longitude": "0.00000000",
						"name": null,
						"orbit_period": null,
						"parent_id": "2030",
						"sensor_danger": "0",
						"sensor_economy": "0",
						"sensor_population": "0",
						"shader_data": null,
						"show_label": "1",
						"show_orbitlines": "1",
						"size": "0.00000000",
						"subtype_id": "51",
						"time_modified": "2015-10-08 03:57:08",
						"type": "ASTEROID_BELT",
						"subtype": {
							"id": "51",
							"name": "Planetary Ring",
							"type": "ASTEROID_BELT"
						},
						"affiliation": [],
						"population": []
					},
					{
						"id": "2042",
						"age": "0.00000000",
						"appearance": "DEFAULT",
						"axial_tilt": "0.00000000",
						"code": "SOL.PLANETS.TITAN",
						"description": "Saturn\u2019s largest natural satellite has long been of great interest to scientists. With rivers and lakes of ethane and methane, Titan is the only moon in the Sol System with a dense atmosphere. ",
						"designation": "Sol 6a",
						"distance": "0.00793247",
						"fairchanceact": null,
						"habitable": null,
						"info_url": null,
						"latitude": "20.21910000",
						"longitude": "-133.33600000",
						"name": "Titan",
						"orbit_period": "16.94500000",
						"parent_id": "2029",
						"sensor_danger": "0",
						"sensor_economy": "0",
						"sensor_population": "0",
						"shader_data": {
							"orbitalMin": 1,
							"orbitalMax": 5,
							"orbitalFactor": 1,
							"highlight": {
								"color1": "rgb(255,255,255)",
								"color2": "rgb(255,255,255)",
								"alpha": 1,
								"atmosphere1": 0.5,
								"atmosphere2": 0.5,
								"atmosphere3": 0.5,
								"scaleMin": 1,
								"scaleMax": 1,
								"scalePeriod": 1
							},
							"radius": 0.005
						},
						"show_label": null,
						"show_orbitlines": null,
						"size": "1.00000000",
						"subtype_id": "52",
						"time_modified": "2015-10-09 17:18:28",
						"type": "SATELLITE",
						"subtype": {
							"id": "52",
							"name": "Planetary Moon",
							"type": "SATELLITE"
						},
						"affiliation": [],
						"population": [],
						"texture": {
							"slug": "3s8vnafjwn09p",
							"source": "https://robertsspaceindustries.com/media/3s8vnafjwn09pr/source/Planet_Chthonian.jpg",
							"images": {
								"post": "https://robertsspaceindustries.com/media/3s8vnafjwn09pr/post/Planet_Chthonian.jpg",
								"product_thumb_large": "https://robertsspaceindustries.com/media/3s8vnafjwn09pr/product_thumb_large/Planet_Chthonian.jpg",
								"subscribers_vault_thumbnail": "https://robertsspaceindustries.com/media/3s8vnafjwn09pr/subscribers_vault_thumbnail/Planet_Chthonian.jpg"
							}
						}
					},
					{
						"id": "2043",
						"age": "0.00000000",
						"appearance": "DEFAULT",
						"axial_tilt": "0.00000000",
						"code": "SOL.PLANETS.RHEA",
						"description": "Made mainly of rock and ice, Rhea is commonly referred to as a \u201cdirty snowball\u201d due to its composition.",
						"designation": "Sol 6b",
						"distance": "0.00352350",
						"fairchanceact": null,
						"habitable": null,
						"info_url": null,
						"latitude": "23.62590000",
						"longitude": "142.73000000",
						"name": "Rhea",
						"orbit_period": "4.51821000",
						"parent_id": "2029",
						"sensor_danger": "0",
						"sensor_economy": "0",
						"sensor_population": "0",
						"shader_data": {
							"orbitalMin": 1,
							"orbitalMax": 5,
							"orbitalFactor": 1,
							"highlight": {
								"color1": "rgb(255,255,255)",
								"color2": "rgb(255,255,255)",
								"alpha": 1,
								"atmosphere1": 0.5,
								"atmosphere2": 0.5,
								"atmosphere3": 0.5,
								"scaleMin": 1,
								"scaleMax": 1,
								"scalePeriod": 1
							},
							"radius": 0.004
						},
						"show_label": null,
						"show_orbitlines": null,
						"size": "1.00000000",
						"subtype_id": "52",
						"time_modified": "2015-10-09 17:18:28",
						"type": "SATELLITE",
						"subtype": {
							"id": "52",
							"name": "Planetary Moon",
							"type": "SATELLITE"
						},
						"affiliation": [],
						"population": [],
						"texture": {
							"slug": "j52x7qoth74yi",
							"source": "https://robertsspaceindustries.com/media/j52x7qoth74yir/source/Planet_Ice.jpg",
							"images": {
								"post": "https://robertsspaceindustries.com/media/j52x7qoth74yir/post/Planet_Ice.jpg",
								"product_thumb_large": "https://robertsspaceindustries.com/media/j52x7qoth74yir/product_thumb_large/Planet_Ice.jpg",
								"subscribers_vault_thumbnail": "https://robertsspaceindustries.com/media/j52x7qoth74yir/subscribers_vault_thumbnail/Planet_Ice.jpg"
							}
						}
					},
					{
						"id": "2044",
						"age": "0.00000000",
						"appearance": "DEFAULT",
						"axial_tilt": "0.00000000",
						"code": "SOL.PLANETS.TETHYS",
						"description": "Tethys is predominantly made of water ice, which gives it a density much lower than other celestial objects its size.  ",
						"designation": "Sol 6c",
						"distance": "0.00196941",
						"fairchanceact": null,
						"habitable": null,
						"info_url": null,
						"latitude": "27.83160000",
						"longitude": "152.08400000",
						"name": "Tethys",
						"orbit_period": "1.88780000",
						"parent_id": "2029",
						"sensor_danger": "0",
						"sensor_economy": "0",
						"sensor_population": "0",
						"shader_data": {
							"orbitalMin": 1,
							"orbitalMax": 5,
							"orbitalFactor": 1,
							"highlight": {
								"color1": "rgb(255,255,255)",
								"color2": "rgb(255,255,255)",
								"alpha": 1,
								"atmosphere1": 0.5,
								"atmosphere2": 0.5,
								"atmosphere3": 0.5,
								"scaleMin": 1,
								"scaleMax": 1,
								"scalePeriod": 1
							},
							"radius": 0.005
						},
						"show_label": null,
						"show_orbitlines": null,
						"size": "1.00000000",
						"subtype_id": "52",
						"time_modified": "2015-10-09 17:18:27",
						"type": "SATELLITE",
						"subtype": {
							"id": "52",
							"name": "Planetary Moon",
							"type": "SATELLITE"
						},
						"affiliation": [],
						"population": [],
						"texture": {
							"slug": "j52x7qoth74yi",
							"source": "https://robertsspaceindustries.com/media/j52x7qoth74yir/source/Planet_Ice.jpg",
							"images": {
								"post": "https://robertsspaceindustries.com/media/j52x7qoth74yir/post/Planet_Ice.jpg",
								"product_thumb_large": "https://robertsspaceindustries.com/media/j52x7qoth74yir/product_thumb_large/Planet_Ice.jpg",
								"subscribers_vault_thumbnail": "https://robertsspaceindustries.com/media/j52x7qoth74yir/subscribers_vault_thumbnail/Planet_Ice.jpg"
							}
						}
					},
					{
						"id": "2045",
						"age": "0.00000000",
						"appearance": "DEFAULT",
						"axial_tilt": "0.00000000",
						"code": "SOL.PLANETS.DIONE",
						"description": "Strangely, this tidally locked moon features numerous impact craters on its trailing hemisphere, leading scientist to speculate that heavy bombardment from objects once spun Dione 180 degrees. ",
						"designation": "Sol 6d",
						"distance": "0.00252274",
						"fairchanceact": null,
						"habitable": null,
						"info_url": null,
						"latitude": "-3.58896000",
						"longitude": "-82.85960000",
						"name": "Dione",
						"orbit_period": "2.73692000",
						"parent_id": "2029",
						"sensor_danger": "0",
						"sensor_economy": "0",
						"sensor_population": "0",
						"shader_data": {
							"orbitalMin": 1,
							"orbitalMax": 5,
							"orbitalFactor": 1,
							"highlight": {
								"color1": "rgb(255,255,255)",
								"color2": "rgb(255,255,255)",
								"alpha": 1,
								"atmosphere1": 0.5,
								"atmosphere2": 0.5,
								"atmosphere3": 0.5,
								"scaleMin": 1,
								"scaleMax": 1,
								"scalePeriod": 1
							},
							"radius": 0.005
						},
						"show_label": null,
						"show_orbitlines": null,
						"size": "1.00000000",
						"subtype_id": "52",
						"time_modified": "2016-06-27 22:10:45",
						"type": "SATELLITE",
						"subtype": {
							"id": "52",
							"name": "Planetary Moon",
							"type": "SATELLITE"
						},
						"affiliation": [],
						"population": [],
						"texture": {
							"slug": "9g2xvstat60bi",
							"source": "https://robertsspaceindustries.com/media/9g2xvstat60bir/source/Planet_Moon.jpg",
							"images": {
								"post": "https://robertsspaceindustries.com/media/9g2xvstat60bir/post/Planet_Moon.jpg",
								"product_thumb_large": "https://robertsspaceindustries.com/media/9g2xvstat60bir/product_thumb_large/Planet_Moon.jpg",
								"subscribers_vault_thumbnail": "https://robertsspaceindustries.com/media/9g2xvstat60bir/subscribers_vault_thumbnail/Planet_Moon.jpg"
							}
						}
					},
					{
						"id": "2046",
						"age": "0.00000000",
						"appearance": "DEFAULT",
						"axial_tilt": "0.00000000",
						"code": "SOL.PLANETS.IAPETUS",
						"description": "Tidally locked to Saturn, Iapetus is unusual because of its \u201ctwo-tone\u201d coloration. The side facing Saturn is constantly shrouded in shadow while the more distant side is illuminated. ",
						"designation": "Sol 6e",
						"distance": "0.02380260",
						"fairchanceact": null,
						"habitable": null,
						"info_url": null,
						"latitude": "-16.82370000",
						"longitude": "21.50410000",
						"name": "Iapetus",
						"orbit_period": "79.32150000",
						"parent_id": "2029",
						"sensor_danger": "0",
						"sensor_economy": "0",
						"sensor_population": "0",
						"shader_data": {
							"orbitalMin": 1,
							"orbitalMax": 5,
							"orbitalFactor": 1,
							"highlight": {
								"color1": "rgb(255,255,255)",
								"color2": "rgb(255,255,255)",
								"alpha": 1,
								"atmosphere1": 0.5,
								"atmosphere2": 0.5,
								"atmosphere3": 0.5,
								"scaleMin": 1,
								"scaleMax": 1,
								"scalePeriod": 1
							},
							"radius": 0.004
						},
						"show_label": null,
						"show_orbitlines": null,
						"size": "1.00000000",
						"subtype_id": "52",
						"time_modified": "2015-10-09 17:18:41",
						"type": "SATELLITE",
						"subtype": {
							"id": "52",
							"name": "Planetary Moon",
							"type": "SATELLITE"
						},
						"affiliation": [],
						"population": [],
						"texture": {
							"slug": "9g2xvstat60bi",
							"source": "https://robertsspaceindustries.com/media/9g2xvstat60bir/source/Planet_Moon.jpg",
							"images": {
								"post": "https://robertsspaceindustries.com/media/9g2xvstat60bir/post/Planet_Moon.jpg",
								"product_thumb_large": "https://robertsspaceindustries.com/media/9g2xvstat60bir/product_thumb_large/Planet_Moon.jpg",
								"subscribers_vault_thumbnail": "https://robertsspaceindustries.com/media/9g2xvstat60bir/subscribers_vault_thumbnail/Planet_Moon.jpg"
							}
						}
					},
					{
						"id": "2047",
						"age": "0.00000000",
						"appearance": "DEFAULT",
						"axial_tilt": "0.00000000",
						"code": "SOL.PLANETS.MIRANDA",
						"description": "Miranda is one of the smallest objects in the Sol System known to be in hydrostatic equilibrium. Its extreme and varied topography includes the Verona Rupes, which features the tallest cliff in the system. ",
						"designation": "Sol 7a",
						"distance": "0.00086492",
						"fairchanceact": null,
						"habitable": null,
						"info_url": null,
						"latitude": "109.42200000",
						"longitude": "-87.23100000",
						"name": "Miranda",
						"orbit_period": "1.41348000",
						"parent_id": "2030",
						"sensor_danger": "0",
						"sensor_economy": "0",
						"sensor_population": "0",
						"shader_data": {
							"orbitalMin": 1,
							"orbitalMax": 5,
							"orbitalFactor": 1,
							"highlight": {
								"color1": "rgb(255,255,255)",
								"color2": "rgb(255,255,255)",
								"alpha": 1,
								"atmosphere1": 0.5,
								"atmosphere2": 0.5,
								"atmosphere3": 0.5,
								"scaleMin": 1,
								"scaleMax": 1,
								"scalePeriod": 1
							},
							"radius": 0.003
						},
						"show_label": null,
						"show_orbitlines": null,
						"size": "0.30000000",
						"subtype_id": "52",
						"time_modified": "2015-10-10 00:35:27",
						"type": "SATELLITE",
						"subtype": {
							"id": "52",
							"name": "Planetary Moon",
							"type": "SATELLITE"
						},
						"affiliation": [],
						"population": [],
						"texture": {
							"slug": "9g2xvstat60bi",
							"source": "https://robertsspaceindustries.com/media/9g2xvstat60bir/source/Planet_Moon.jpg",
							"images": {
								"post": "https://robertsspaceindustries.com/media/9g2xvstat60bir/post/Planet_Moon.jpg",
								"product_thumb_large": "https://robertsspaceindustries.com/media/9g2xvstat60bir/product_thumb_large/Planet_Moon.jpg",
								"subscribers_vault_thumbnail": "https://robertsspaceindustries.com/media/9g2xvstat60bir/subscribers_vault_thumbnail/Planet_Moon.jpg"
							}
						}
					},
					{
						"id": "2048",
						"age": "0.00000000",
						"appearance": "DEFAULT",
						"axial_tilt": "0.00000000",
						"code": "SOL.PLANETS.ARIAL",
						"description": "The surface of this moon is crisscrossed by an extensive network of scarps, canyons, and ridges. Scientists speculate some of these canyons were carved out by liquid ammonia, methane, or carbon monoxide.  ",
						"designation": "Sol 7b",
						"distance": "0.00127609",
						"fairchanceact": null,
						"habitable": null,
						"info_url": null,
						"latitude": "-12.89247000",
						"longitude": "79.39630000",
						"name": "Ariel",
						"orbit_period": "2.52000000",
						"parent_id": "2030",
						"sensor_danger": "0",
						"sensor_economy": "0",
						"sensor_population": "0",
						"shader_data": null,
						"show_label": null,
						"show_orbitlines": null,
						"size": "0.60000000",
						"subtype_id": "52",
						"time_modified": "2015-10-10 05:30:39",
						"type": "SATELLITE",
						"subtype": {
							"id": "52",
							"name": "Planetary Moon",
							"type": "SATELLITE"
						},
						"affiliation": [],
						"population": []
					},
					{
						"id": "2049",
						"age": "0.00000000",
						"appearance": "DEFAULT",
						"axial_tilt": "0.00000000",
						"code": "SOL.PLANETS.UMBRIEL",
						"description": "This moon\u2019s name has its roots in the Latin word \u201cumbra\u201d, which means shadow. An appropriate reference considering Umbriel is the darkest of all Uranian moons. ",
						"designation": "Sol 7c",
						"distance": "0.00177810",
						"fairchanceact": null,
						"habitable": null,
						"info_url": null,
						"latitude": "-14.56740000",
						"longitude": "-77.15400000",
						"name": "Umbriel",
						"orbit_period": "4.14400000",
						"parent_id": "2030",
						"sensor_danger": "0",
						"sensor_economy": "0",
						"sensor_population": "0",
						"shader_data": {
							"orbitalMin": 1,
							"orbitalMax": 5,
							"orbitalFactor": 1,
							"highlight": {
								"color1": "rgb(255,255,255)",
								"color2": "rgb(255,255,255)",
								"alpha": 1,
								"atmosphere1": 0.5,
								"atmosphere2": 0.5,
								"atmosphere3": 0.5,
								"scaleMin": 1,
								"scaleMax": 1,
								"scalePeriod": 1
							},
							"radius": 0.004
						},
						"show_label": null,
						"show_orbitlines": null,
						"size": "0.65000000",
						"subtype_id": "52",
						"time_modified": "2015-10-10 00:33:53",
						"type": "SATELLITE",
						"subtype": {
							"id": "52",
							"name": "Planetary Moon",
							"type": "SATELLITE"
						},
						"affiliation": [],
						"population": [],
						"texture": {
							"slug": "jnd5qqer9z13g",
							"source": "https://robertsspaceindustries.com/media/jnd5qqer9z13gr/source/Planet_Rocky.jpg",
							"images": {
								"post": "https://robertsspaceindustries.com/media/jnd5qqer9z13gr/post/Planet_Rocky.jpg",
								"product_thumb_large": "https://robertsspaceindustries.com/media/jnd5qqer9z13gr/product_thumb_large/Planet_Rocky.jpg",
								"subscribers_vault_thumbnail": "https://robertsspaceindustries.com/media/jnd5qqer9z13gr/subscribers_vault_thumbnail/Planet_Rocky.jpg"
							}
						}
					},
					{
						"id": "2050",
						"age": "0.00000000",
						"appearance": "DEFAULT",
						"axial_tilt": "0.00000000",
						"code": "SOL.PLANETS.TITANIA",
						"description": "Titania is Uranus\u2019 largest moon. Enormous canyons and scarps cut through its surface. Scientists believe they were created after an interior expansion occurred during the moon\u2019s evolution.",
						"designation": "Sol 7d",
						"distance": "0.00291388",
						"fairchanceact": null,
						"habitable": null,
						"info_url": null,
						"latitude": "31.37106000",
						"longitude": "-98.67700000",
						"name": "Titania",
						"orbit_period": "8.70623000",
						"parent_id": "2030",
						"sensor_danger": "0",
						"sensor_economy": "0",
						"sensor_population": "0",
						"shader_data": {
							"orbitalMin": 1,
							"orbitalMax": 5,
							"orbitalFactor": 1,
							"highlight": {
								"color1": "rgb(255,255,255)",
								"color2": "rgb(255,255,255)",
								"alpha": 1,
								"atmosphere1": 0.5,
								"atmosphere2": 0.5,
								"atmosphere3": 0.5,
								"scaleMin": 1,
								"scaleMax": 1,
								"scalePeriod": 1
							},
							"radius": 0.005
						},
						"show_label": null,
						"show_orbitlines": null,
						"size": "0.80000000",
						"subtype_id": "52",
						"time_modified": "2015-10-10 05:27:13",
						"type": "SATELLITE",
						"subtype": {
							"id": "52",
							"name": "Planetary Moon",
							"type": "SATELLITE"
						},
						"affiliation": [],
						"population": [],
						"texture": {
							"slug": "9g2xvstat60bi",
							"source": "https://robertsspaceindustries.com/media/9g2xvstat60bir/source/Planet_Moon.jpg",
							"images": {
								"post": "https://robertsspaceindustries.com/media/9g2xvstat60bir/post/Planet_Moon.jpg",
								"product_thumb_large": "https://robertsspaceindustries.com/media/9g2xvstat60bir/product_thumb_large/Planet_Moon.jpg",
								"subscribers_vault_thumbnail": "https://robertsspaceindustries.com/media/9g2xvstat60bir/subscribers_vault_thumbnail/Planet_Moon.jpg"
							}
						}
					},
					{
						"id": "2051",
						"age": "0.00000000",
						"appearance": "DEFAULT",
						"axial_tilt": "0.00000000",
						"code": "SOL.PLANETS.OBERON",
						"description": "Uranus\u2019 second largest moon was named after a mythical faery king from a famous 16th century play. Its surface is covered in impact craters and appears red in color due to space weathering.",
						"designation": "Sol 7e",
						"distance": "0.00310059",
						"fairchanceact": null,
						"habitable": null,
						"info_url": null,
						"latitude": "-84.39090000",
						"longitude": "-2.12600000",
						"name": "Oberon",
						"orbit_period": "13.46320000",
						"parent_id": "2030",
						"sensor_danger": "0",
						"sensor_economy": "0",
						"sensor_population": "0",
						"shader_data": {
							"orbitalMin": 1,
							"orbitalMax": 5,
							"orbitalFactor": 1,
							"highlight": {
								"color1": "rgb(255,255,255)",
								"color2": "rgb(255,255,255)",
								"alpha": 1,
								"atmosphere1": 0.5,
								"atmosphere2": 0.5,
								"atmosphere3": 0.5,
								"scaleMin": 1,
								"scaleMax": 1,
								"scalePeriod": 1
							},
							"radius": 0.005
						},
						"show_label": null,
						"show_orbitlines": null,
						"size": "0.75000000",
						"subtype_id": "52",
						"time_modified": "2015-10-10 00:45:09",
						"type": "SATELLITE",
						"subtype": {
							"id": "52",
							"name": "Planetary Moon",
							"type": "SATELLITE"
						},
						"affiliation": [],
						"population": [],
						"texture": {
							"slug": "dgaoam8owcym1",
							"source": "https://robertsspaceindustries.com/media/dgaoam8owcym1r/source/Planet_Lava.jpg",
							"images": {
								"post": "https://robertsspaceindustries.com/media/dgaoam8owcym1r/post/Planet_Lava.jpg",
								"product_thumb_large": "https://robertsspaceindustries.com/media/dgaoam8owcym1r/product_thumb_large/Planet_Lava.jpg",
								"subscribers_vault_thumbnail": "https://robertsspaceindustries.com/media/dgaoam8owcym1r/subscribers_vault_thumbnail/Planet_Lava.jpg"
							}
						}
					},
					{
						"id": "2052",
						"age": "0.00000000",
						"appearance": "DEFAULT",
						"axial_tilt": "0.00000000",
						"code": "SOL.BELTS.MAINBELT",
						"description": "Over half the belt\u2019s entire mass is concentrated in four large asteroids. ",
						"designation": "Sol Belt Alpha",
						"distance": "2.70000000",
						"fairchanceact": null,
						"habitable": null,
						"info_url": null,
						"latitude": "0.00000000",
						"longitude": "0.00000000",
						"name": "Herschel Belt",
						"orbit_period": null,
						"parent_id": "2023",
						"sensor_danger": "2",
						"sensor_economy": "3",
						"sensor_population": "1",
						"shader_data": null,
						"show_label": "1",
						"show_orbitlines": null,
						"size": "0.00000000",
						"subtype_id": "50",
						"time_modified": "2015-10-08 14:18:08",
						"type": "ASTEROID_BELT",
						"subtype": {
							"id": "50",
							"name": "System Belt",
							"type": "ASTEROID_BELT"
						},
						"affiliation": [],
						"population": []
					},
					{
						"id": "2053",
						"age": "0.00000000",
						"appearance": "DEFAULT",
						"axial_tilt": "0.00000000",
						"code": "SOL.BELTS.KEUPERBELT",
						"description": "The Kuiper Belt consists mainly of small bodies that are believed to be remnants from Sol's formation.",
						"designation": "Sol Belt Beta",
						"distance": "45.00000000",
						"fairchanceact": null,
						"habitable": null,
						"info_url": null,
						"latitude": "0.00000000",
						"longitude": "0.00000000",
						"name": "Kuiper Belt",
						"orbit_period": null,
						"parent_id": "2023",
						"sensor_danger": "2",
						"sensor_economy": "3",
						"sensor_population": "1",
						"shader_data": {
							"orbitalMin": 1,
							"orbitalMax": 5,
							"orbitalFactor": 1,
							"orbitalColor": "rgb(26,86,124)",
							"orbitalHighlightColor": "rgb(128,128,255)",
							"fullturn": 1,
							"radius": 0.4
						},
						"show_label": "1",
						"show_orbitlines": null,
						"size": "99999999.99999999",
						"subtype_id": "50",
						"time_modified": "2015-10-20 19:18:31",
						"type": "ASTEROID_BELT",
						"subtype": {
							"id": "50",
							"name": "System Belt",
							"type": "ASTEROID_BELT"
						},
						"affiliation": [],
						"population": []
					},
					{
						"id": "2610",
						"age": null,
						"appearance": "DEFAULT",
						"axial_tilt": null,
						"code": "SOL.STATION.TDDKESNER",
						"description": "A major shipping hub where most cargo moving to Earth is first processed to help alleviate congestion on the Empire\u2019s capital world. \n",
						"designation": "TDD Kesner",
						"distance": "51.00000000",
						"fairchanceact": null,
						"habitable": "1",
						"info_url": null,
						"latitude": "-4.19421000",
						"longitude": "86.21810000",
						"name": null,
						"orbit_period": null,
						"parent_id": "2023",
						"sensor_danger": "3",
						"sensor_economy": "8",
						"sensor_population": "3",
						"shader_data": null,
						"show_label": "1",
						"show_orbitlines": "1",
						"size": null,
						"subtype_id": "44",
						"time_modified": "2015-10-09 02:01:43",
						"type": "MANMADE",
						"subtype": {
							"id": "44",
							"name": "Space Station",
							"type": "MANMADE"
						},
						"affiliation": [
							{
								"id": "1",
								"code": "uee",
								"color": "#48bbd4",
								"name": "UEE",
								"membership.id": "2266"
							}
						],
						"population": []
					},
					{
						"id": "2612",
						"age": null,
						"appearance": "DEFAULT",
						"axial_tilt": null,
						"code": "SOL.STATION.IMSBOLLIVER",
						"description": "Though it is no longer in active service since the Marine forces stationed here were reassigned to Mars, the base remains strictly off limits. ",
						"designation": "IMS Bolliver",
						"distance": "0.00030100",
						"fairchanceact": null,
						"habitable": "1",
						"info_url": null,
						"latitude": null,
						"longitude": "12.65498000",
						"name": null,
						"orbit_period": null,
						"parent_id": "2036",
						"sensor_danger": "5",
						"sensor_economy": "1",
						"sensor_population": "1",
						"shader_data": null,
						"show_label": "1",
						"show_orbitlines": "1",
						"size": null,
						"subtype_id": "44",
						"time_modified": "2015-10-09 17:16:16",
						"type": "MANMADE",
						"subtype": {
							"id": "44",
							"name": "Space Station",
							"type": "MANMADE"
						},
						"affiliation": [],
						"population": []
					},
					{
						"id": "2613",
						"age": null,
						"appearance": "DEFAULT",
						"axial_tilt": null,
						"code": "SOL.STATION.INSDUNLEAVY",
						"description": "This orbital Naval base acts as the main operational center for the main Sol fleet.",
						"designation": "INS Dunleavy",
						"distance": "16.30000000",
						"fairchanceact": null,
						"habitable": "1",
						"info_url": null,
						"latitude": "25.28630000",
						"longitude": "-129.96200000",
						"name": null,
						"orbit_period": null,
						"parent_id": "2023",
						"sensor_danger": "1",
						"sensor_economy": "5",
						"sensor_population": "4",
						"shader_data": null,
						"show_label": "1",
						"show_orbitlines": "1",
						"size": null,
						"subtype_id": "44",
						"time_modified": "2015-10-09 02:00:29",
						"type": "MANMADE",
						"subtype": {
							"id": "44",
							"name": "Space Station",
							"type": "MANMADE"
						},
						"affiliation": [
							{
								"id": "1",
								"code": "uee",
								"color": "#48bbd4",
								"name": "UEE",
								"membership.id": "2265"
							}
						],
						"population": []
					},
					{
						"id": "2757",
						"age": null,
						"appearance": "DEFAULT",
						"axial_tilt": null,
						"code": "SOL.MOONS.PHOBOS",
						"description": "Only 6,000 kilometers away, Phobos orbits Mars so fast that it appears to rise in the west and set in the east twice every Martian day. ",
						"designation": "Sol 4a",
						"distance": "0.00062300",
						"fairchanceact": null,
						"habitable": null,
						"info_url": null,
						"latitude": "34.00000000",
						"longitude": "156.00000000",
						"name": "Phobos",
						"orbit_period": null,
						"parent_id": "2027",
						"sensor_danger": "0",
						"sensor_economy": "0",
						"sensor_population": "0",
						"shader_data": null,
						"show_label": null,
						"show_orbitlines": null,
						"size": "0.11000000",
						"subtype_id": "52",
						"time_modified": "2016-06-30 00:47:09",
						"type": "SATELLITE",
						"subtype": {
							"id": "52",
							"name": "Planetary Moon",
							"type": "SATELLITE"
						},
						"affiliation": [],
						"population": []
					},
					{
						"id": "2758",
						"age": null,
						"appearance": "DEFAULT",
						"axial_tilt": null,
						"code": "SOL.MOONS.DEIMOS",
						"description": "With a radius of only 6.2 kilometers, Deimos' size and lumpy shape bear more of a resemblance to an asteroid than a moon. ",
						"designation": "Sol 4b",
						"distance": "0.00082500",
						"fairchanceact": null,
						"habitable": null,
						"info_url": null,
						"latitude": null,
						"longitude": null,
						"name": "Deimos",
						"orbit_period": null,
						"parent_id": "2027",
						"sensor_danger": "0",
						"sensor_economy": "0",
						"sensor_population": "0",
						"shader_data": null,
						"show_label": null,
						"show_orbitlines": null,
						"size": "0.06200000",
						"subtype_id": "52",
						"time_modified": "2016-06-30 00:47:24",
						"type": "SATELLITE",
						"subtype": {
							"id": "52",
							"name": "Planetary Moon",
							"type": "SATELLITE"
						},
						"affiliation": [],
						"population": []
					},
					{
						"id": "2774",
						"age": null,
						"appearance": "DEFAULT",
						"axial_tilt": null,
						"code": "SOL.MOONS.CHARON",
						"description": "The gravitational influence of Charon on Pluto is such that the pair has been classified and unclassified as a binary dwarf planet multiple times since its discovery in 1978. ",
						"designation": "Sol 9a",
						"distance": "0.00013082",
						"fairchanceact": null,
						"habitable": null,
						"info_url": null,
						"latitude": null,
						"longitude": null,
						"name": "Charon",
						"orbit_period": null,
						"parent_id": "2032",
						"sensor_danger": "2",
						"sensor_economy": "1",
						"sensor_population": "1",
						"shader_data": null,
						"show_label": null,
						"show_orbitlines": null,
						"size": "1.60400000",
						"subtype_id": "52",
						"time_modified": "2016-06-27 17:50:31",
						"type": "SATELLITE",
						"subtype": {
							"id": "52",
							"name": "Planetary Moon",
							"type": "SATELLITE"
						},
						"affiliation": [],
						"population": [],
						"texture": {
							"slug": "9g2xvstat60bi",
							"source": "https://robertsspaceindustries.com/media/9g2xvstat60bir/source/Planet_Moon.jpg",
							"images": {
								"post": "https://robertsspaceindustries.com/media/9g2xvstat60bir/post/Planet_Moon.jpg",
								"product_thumb_large": "https://robertsspaceindustries.com/media/9g2xvstat60bir/product_thumb_large/Planet_Moon.jpg",
								"subscribers_vault_thumbnail": "https://robertsspaceindustries.com/media/9g2xvstat60bir/subscribers_vault_thumbnail/Planet_Moon.jpg"
							}
						}
					}
				],
				"aggregated_size": "51.00000000",
				"aggregated_population": 8.59,
				"aggregated_economy": 5.58,
				"aggregated_danger": 0
			}
		]
	}
}